[
  {
      "info": {
          "id": "272031",
          "name": "Baskin Robbins",
          "cloudinaryImageId": "85ccae4e3576f9330af102c46ca85395",
          "locality": "5th Block",
          "areaName": "Koramangala",
          "costForTwo": "₹150 for two",
          "cuisines": [
              "Desserts"
          ],
          "avgRating": 4.4,
          "veg": true,
          "parentId": "5588",
          "avgRatingString": "4.4",
          "totalRatingsString": "100+",
          "sla": {
              "deliveryTime": 26,
              "lastMileTravel": 2.3,
              "serviceability": "SERVICEABLE",
              "slaString": "25-30 mins",
              "lastMileTravelString": "2.3 km",
              "iconType": "ICON_TYPE_EMPTY"
          },
          "availability": {
              "nextCloseTime": "2024-04-19 00:00:00",
              "opened": true
          },
          "badges": {
              "imageBadges": [
                  {
                      "imageId": "v1695133679/badges/Pure_Veg111.png",
                      "description": "pureveg"
                  }
              ],
              "textExtendedBadges": [
                  {
                      "iconId": "v1705582451/Ratnesh_Badges/Listing_HR.png",
                      "shortDescription": "Perfect Cake Delivery",
                      "fontColor": "#7E808C"
                  }
              ]
          },
          "isOpen": true,
          "type": "F",
          "badgesV2": {
              "entityBadges": {
                  "imageBased": {
                      "badgeObject": [
                          {
                              "attributes": {
                                  "description": "pureveg",
                                  "imageId": "v1695133679/badges/Pure_Veg111.png"
                              }
                          }
                      ]
                  },
                  "textBased": {},
                  "textExtendedBadges": {
                      "badgeObject": [
                          {
                              "attributes": {
                                  "description": "",
                                  "fontColor": "#7E808C",
                                  "iconId": "v1705582451/Ratnesh_Badges/Listing_HR.png",
                                  "shortDescription": "Perfect Cake Delivery"
                              }
                          }
                      ]
                  }
              }
          },
          "aggregatedDiscountInfoV3": {
              "header": "50% OFF",
              "subHeader": "UPTO ₹100"
          },
          "differentiatedUi": {
              "displayType": "ADS_UI_DISPLAY_TYPE_ENUM_DEFAULT",
              "differentiatedUiMediaDetails": {
                  "mediaType": "ADS_MEDIA_ENUM_IMAGE",
                  "lottie": {},
                  "video": {}
              }
          },
          "reviewsSummary": {},
          "displayType": "RESTAURANT_DISPLAY_TYPE_DEFAULT",
          "restaurantOfferPresentationInfo": {}
      },
      "analytics": {},
      "cta": {
          "link": "https://www.swiggy.com/restaurants/baskin-robbins-5th-block-koramangala-bangalore-272031",
          "type": "WEBLINK"
      }
  },
  {
      "info": {
          "id": "74444",
          "name": "Samosa Party",
          "cloudinaryImageId": "d8d4e708a41f011361c949d44990d5e0",
          "locality": "Koramangala",
          "areaName": "Koramangala",
          "costForTwo": "₹100 for two",
          "cuisines": [
              "Fast Food",
              "Snacks",
              "Beverages",
              "Chaat",
              "North Indian",
              "Street Food",
              "Sweets",
              "Desserts",
              "Punjabi",
              "Bakery"
          ],
          "avgRating": 4.3,
          "parentId": "6364",
          "avgRatingString": "4.3",
          "totalRatingsString": "10K+",
          "sla": {
              "deliveryTime": 28,
              "lastMileTravel": 2.3,
              "serviceability": "SERVICEABLE",
              "slaString": "25-30 mins",
              "lastMileTravelString": "2.3 km",
              "iconType": "ICON_TYPE_EMPTY"
          },
          "availability": {
              "nextCloseTime": "2024-04-19 00:00:00",
              "opened": true
          },
          "badges": {
              "textExtendedBadges": [
                  {
                      "iconId": "guiltfree/GF_Logo_android_3x",
                      "shortDescription": "options available",
                      "fontColor": "#7E808C"
                  }
              ]
          },
          "isOpen": true,
          "type": "F",
          "badgesV2": {
              "entityBadges": {
                  "imageBased": {},
                  "textBased": {},
                  "textExtendedBadges": {
                      "badgeObject": [
                          {
                              "attributes": {
                                  "description": "",
                                  "fontColor": "#7E808C",
                                  "iconId": "guiltfree/GF_Logo_android_3x",
                                  "shortDescription": "options available"
                              }
                          }
                      ]
                  }
              }
          },
          "aggregatedDiscountInfoV3": {
              "header": "60% OFF",
              "subHeader": "UPTO ₹120"
          },
          "differentiatedUi": {
              "displayType": "ADS_UI_DISPLAY_TYPE_ENUM_DEFAULT",
              "differentiatedUiMediaDetails": {
                  "mediaType": "ADS_MEDIA_ENUM_IMAGE",
                  "lottie": {},
                  "video": {}
              }
          },
          "reviewsSummary": {},
          "displayType": "RESTAURANT_DISPLAY_TYPE_DEFAULT",
          "restaurantOfferPresentationInfo": {}
      },
      "analytics": {},
      "cta": {
          "link": "https://www.swiggy.com/restaurants/samosa-party-koramangala-bangalore-74444",
          "type": "WEBLINK"
      }
  },
  {
      "info": {
          "id": "408386",
          "name": "NOTO - Ice Creams & Desserts",
          "cloudinaryImageId": "81ac87e5c89c16adc867be38ce5a1ba3",
          "locality": "Ejipura",
          "areaName": "Koramangla",
          "costForTwo": "₹250 for two",
          "cuisines": [
              "Ice Cream"
          ],
          "avgRating": 4.4,
          "veg": true,
          "parentId": "468478",
          "avgRatingString": "4.4",
          "totalRatingsString": "1K+",
          "sla": {
              "deliveryTime": 17,
              "lastMileTravel": 1.1,
              "serviceability": "SERVICEABLE",
              "slaString": "15-20 mins",
              "lastMileTravelString": "1.1 km",
              "iconType": "ICON_TYPE_EMPTY"
          },
          "availability": {
              "nextCloseTime": "2024-04-13 05:55:00",
              "opened": true
          },
          "badges": {
              "textExtendedBadges": [
                  {
                      "iconId": "guiltfree/GF_Logo_android_3x",
                      "shortDescription": "brand",
                      "fontColor": "#7E808C"
                  }
              ]
          },
          "isOpen": true,
          "type": "F",
          "badgesV2": {
              "entityBadges": {
                  "imageBased": {},
                  "textBased": {},
                  "textExtendedBadges": {
                      "badgeObject": [
                          {
                              "attributes": {
                                  "description": "",
                                  "fontColor": "#7E808C",
                                  "iconId": "guiltfree/GF_Logo_android_3x",
                                  "shortDescription": "brand"
                              }
                          }
                      ]
                  }
              }
          },
          "aggregatedDiscountInfoV3": {
              "header": "60% OFF",
              "subHeader": "UPTO ₹120"
          },
          "differentiatedUi": {
              "displayType": "ADS_UI_DISPLAY_TYPE_ENUM_DEFAULT",
              "differentiatedUiMediaDetails": {
                  "mediaType": "ADS_MEDIA_ENUM_IMAGE",
                  "lottie": {},
                  "video": {}
              }
          },
          "reviewsSummary": {},
          "displayType": "RESTAURANT_DISPLAY_TYPE_DEFAULT",
          "restaurantOfferPresentationInfo": {}
      },
      "analytics": {},
      "cta": {
          "link": "https://www.swiggy.com/restaurants/noto-ice-creams-and-desserts-ejipura-koramangla-bangalore-408386",
          "type": "WEBLINK"
      }
  },
  {
      "info": {
          "id": "1308",
          "name": "Rolls On Wheels - Shawarma & Wraps",
          "cloudinaryImageId": "e3493cc67c8215a1a18ba31822184fe3",
          "locality": "HSR Layout",
          "areaName": "HSR Layout",
          "costForTwo": "₹300 for two",
          "cuisines": [
              "Fast Food",
              "Snacks",
              "Bengali",
              "Kebabs",
              "Beverages",
              "Healthy Food",
              "Chinese"
          ],
          "avgRating": 4.3,
          "parentId": "493982",
          "avgRatingString": "4.3",
          "totalRatingsString": "10K+",
          "sla": {
              "deliveryTime": 30,
              "lastMileTravel": 4.8,
              "serviceability": "SERVICEABLE",
              "slaString": "30-35 mins",
              "lastMileTravelString": "4.8 km",
              "iconType": "ICON_TYPE_EMPTY"
          },
          "availability": {
              "nextCloseTime": "2024-04-12 07:00:00",
              "opened": true
          },
          "badges": {
              "imageBadges": [
                  {
                      "imageId": "Rxawards/_CATEGORY-Rolls.png",
                      "description": "Delivery!"
                  }
              ]
          },
          "isOpen": true,
          "type": "F",
          "badgesV2": {
              "entityBadges": {
                  "imageBased": {
                      "badgeObject": [
                          {
                              "attributes": {
                                  "description": "Delivery!",
                                  "imageId": "Rxawards/_CATEGORY-Rolls.png"
                              }
                          }
                      ]
                  },
                  "textBased": {},
                  "textExtendedBadges": {}
              }
          },
          "aggregatedDiscountInfoV3": {
              "header": "50% OFF",
              "subHeader": "UPTO ₹100"
          },
          "differentiatedUi": {
              "displayType": "ADS_UI_DISPLAY_TYPE_ENUM_DEFAULT",
              "differentiatedUiMediaDetails": {
                  "mediaType": "ADS_MEDIA_ENUM_IMAGE",
                  "lottie": {},
                  "video": {}
              }
          },
          "reviewsSummary": {},
          "displayType": "RESTAURANT_DISPLAY_TYPE_DEFAULT",
          "restaurantOfferPresentationInfo": {}
      },
      "analytics": {},
      "cta": {
          "link": "https://www.swiggy.com/restaurants/rolls-on-wheels-shawarma-and-wraps-hsr-layout-bangalore-1308",
          "type": "WEBLINK"
      }
  },
  {
      "info": {
          "id": "676",
          "name": "Chai Point",
          "cloudinaryImageId": "ygpt52g5s8fzopfaac2l",
          "locality": "Kora 6th block",
          "areaName": "Koramangala",
          "costForTwo": "₹150 for two",
          "cuisines": [
              "Bakery",
              "Beverages",
              "Maharashtrian",
              "Snacks",
              "Street Food",
              "South Indian",
              "Punjabi",
              "Chaat",
              "Indian",
              "American",
              "Fast Food",
              "Desserts",
              "Cafe",
              "Healthy Food",
              "Home Food",
              "North Indian"
          ],
          "avgRating": 4.3,
          "parentId": "1607",
          "avgRatingString": "4.3",
          "totalRatingsString": "10K+",
          "sla": {
              "deliveryTime": 33,
              "lastMileTravel": 1,
              "serviceability": "SERVICEABLE",
              "slaString": "30-35 mins",
              "lastMileTravelString": "1.0 km",
              "iconType": "ICON_TYPE_EMPTY"
          },
          "availability": {
              "nextCloseTime": "2024-04-12 23:00:00",
              "opened": true
          },
          "badges": {
              "imageBadges": [
                  {
                      "imageId": "Rxawards/_CATEGORY-Cafe%20&%20Chai.png",
                      "description": "Delivery!"
                  }
              ]
          },
          "isOpen": true,
          "type": "F",
          "badgesV2": {
              "entityBadges": {
                  "imageBased": {
                      "badgeObject": [
                          {
                              "attributes": {
                                  "description": "Delivery!",
                                  "imageId": "Rxawards/_CATEGORY-Cafe%20&%20Chai.png"
                              }
                          }
                      ]
                  },
                  "textBased": {},
                  "textExtendedBadges": {}
              }
          },
          "aggregatedDiscountInfoV3": {
              "header": "₹125 OFF",
              "subHeader": "ABOVE ₹249",
              "discountTag": "FLAT DEAL"
          },
          "differentiatedUi": {
              "displayType": "ADS_UI_DISPLAY_TYPE_ENUM_DEFAULT",
              "differentiatedUiMediaDetails": {
                  "mediaType": "ADS_MEDIA_ENUM_IMAGE",
                  "lottie": {},
                  "video": {}
              }
          },
          "reviewsSummary": {},
          "displayType": "RESTAURANT_DISPLAY_TYPE_DEFAULT",
          "restaurantOfferPresentationInfo": {}
      },
      "analytics": {},
      "cta": {
          "link": "https://www.swiggy.com/restaurants/chai-point-kora-6th-block-koramangala-bangalore-676",
          "type": "WEBLINK"
      }
  },
  {
      "info": {
          "id": "289167",
          "name": "Cafe Coffee Day",
          "cloudinaryImageId": "b70c7d23d197251b7b315b7e4d8173ae",
          "locality": "4th Sector",
          "areaName": "HSR Layout",
          "costForTwo": "₹400 for two",
          "cuisines": [
              "Beverages",
              "Cafe",
              "Snacks",
              "Desserts",
              "Burgers",
              "Ice Cream",
              "Bakery",
              "Fast Food"
          ],
          "avgRating": 4.2,
          "parentId": "1",
          "avgRatingString": "4.2",
          "totalRatingsString": "500+",
          "sla": {
              "deliveryTime": 31,
              "lastMileTravel": 4.4,
              "serviceability": "SERVICEABLE",
              "slaString": "30-35 mins",
              "lastMileTravelString": "4.4 km",
              "iconType": "ICON_TYPE_EMPTY"
          },
          "availability": {
              "nextCloseTime": "2024-04-19 00:00:00",
              "opened": true
          },
          "badges": {
              "textExtendedBadges": [
                  {
                      "iconId": "guiltfree/GF_Logo_android_3x",
                      "shortDescription": "options available",
                      "fontColor": "#7E808C"
                  }
              ]
          },
          "isOpen": true,
          "type": "F",
          "badgesV2": {
              "entityBadges": {
                  "imageBased": {},
                  "textBased": {},
                  "textExtendedBadges": {
                      "badgeObject": [
                          {
                              "attributes": {
                                  "description": "",
                                  "fontColor": "#7E808C",
                                  "iconId": "guiltfree/GF_Logo_android_3x",
                                  "shortDescription": "options available"
                              }
                          }
                      ]
                  }
              }
          },
          "aggregatedDiscountInfoV3": {
              "header": "50% OFF",
              "subHeader": "UPTO ₹100"
          },
          "differentiatedUi": {
              "displayType": "ADS_UI_DISPLAY_TYPE_ENUM_DEFAULT",
              "differentiatedUiMediaDetails": {
                  "mediaType": "ADS_MEDIA_ENUM_IMAGE",
                  "lottie": {},
                  "video": {}
              }
          },
          "reviewsSummary": {},
          "displayType": "RESTAURANT_DISPLAY_TYPE_DEFAULT",
          "restaurantOfferPresentationInfo": {}
      },
      "analytics": {},
      "cta": {
          "link": "https://www.swiggy.com/restaurants/cafe-coffee-day-4th-sector-hsr-layout-bangalore-289167",
          "type": "WEBLINK"
      }
  },
  {
      "info": {
          "id": "307",
          "name": "A2B - Adyar Ananda Bhavan",
          "cloudinaryImageId": "gxe4mn4ubw70yx3flyar",
          "locality": "1st Stage",
          "areaName": "Btm Layout",
          "costForTwo": "₹300 for two",
          "cuisines": [
              "South Indian",
              "North Indian",
              "Sweets",
              "Chinese"
          ],
          "avgRating": 4.5,
          "veg": true,
          "parentId": "22",
          "avgRatingString": "4.5",
          "totalRatingsString": "10K+",
          "sla": {
              "deliveryTime": 28,
              "lastMileTravel": 4,
              "serviceability": "SERVICEABLE",
              "slaString": "25-30 mins",
              "lastMileTravelString": "4.0 km",
              "iconType": "ICON_TYPE_EMPTY"
          },
          "availability": {
              "nextCloseTime": "2024-04-12 22:30:00",
              "opened": true
          },
          "badges": {
              "imageBadges": [
                  {
                      "imageId": "Rxawards/_CATEGORY-Mithai.png",
                      "description": "Delivery!"
                  },
                  {
                      "imageId": "Rxawards/_CATEGORY-South%20Indian.png",
                      "description": "Delivery!"
                  },
                  {
                      "imageId": "v1695133679/badges/Pure_Veg111.png",
                      "description": "pureveg"
                  }
              ]
          },
          "isOpen": true,
          "type": "F",
          "badgesV2": {
              "entityBadges": {
                  "imageBased": {
                      "badgeObject": [
                          {
                              "attributes": {
                                  "description": "Delivery!",
                                  "imageId": "Rxawards/_CATEGORY-Mithai.png"
                              }
                          },
                          {
                              "attributes": {
                                  "description": "Delivery!",
                                  "imageId": "Rxawards/_CATEGORY-South%20Indian.png"
                              }
                          },
                          {
                              "attributes": {
                                  "description": "pureveg",
                                  "imageId": "v1695133679/badges/Pure_Veg111.png"
                              }
                          }
                      ]
                  },
                  "textBased": {},
                  "textExtendedBadges": {}
              }
          },
          "aggregatedDiscountInfoV3": {
              "header": "20% OFF",
              "subHeader": "UPTO ₹50"
          },
          "differentiatedUi": {
              "displayType": "ADS_UI_DISPLAY_TYPE_ENUM_DEFAULT",
              "differentiatedUiMediaDetails": {
                  "mediaType": "ADS_MEDIA_ENUM_IMAGE",
                  "lottie": {},
                  "video": {}
              }
          },
          "reviewsSummary": {},
          "displayType": "RESTAURANT_DISPLAY_TYPE_DEFAULT",
          "restaurantOfferPresentationInfo": {}
      },
      "analytics": {},
      "cta": {
          "link": "https://www.swiggy.com/restaurants/a2b-adyar-ananda-bhavan-1st-stage-btm-layout-bangalore-307",
          "type": "WEBLINK"
      }
  },
  {
      "info": {
          "id": "402710",
          "name": "WarmOven Cake & Desserts",
          "cloudinaryImageId": "e938fb5f416cc2c28b4b519cf27b04cc",
          "locality": "Millars Road",
          "areaName": "Vasanth Nagar",
          "costForTwo": "₹200 for two",
          "cuisines": [
              "Bakery",
              "Desserts",
              "Ice Cream",
              "Beverages"
          ],
          "avgRating": 3.8,
          "parentId": "9696",
          "avgRatingString": "3.8",
          "totalRatingsString": "500+",
          "sla": {
              "deliveryTime": 61,
              "lastMileTravel": 10.1,
              "serviceability": "SERVICEABLE",
              "slaString": "60-65 mins",
              "lastMileTravelString": "10.1 km",
              "iconType": "ICON_TYPE_EMPTY"
          },
          "availability": {
              "nextCloseTime": "2024-04-19 00:00:00",
              "opened": true
          },
          "badges": {},
          "isOpen": true,
          "type": "F",
          "badgesV2": {
              "entityBadges": {
                  "imageBased": {},
                  "textBased": {},
                  "textExtendedBadges": {}
              }
          },
          "aggregatedDiscountInfoV3": {
              "header": "50% OFF",
              "subHeader": "UPTO ₹100"
          },
          "differentiatedUi": {
              "displayType": "ADS_UI_DISPLAY_TYPE_ENUM_DEFAULT",
              "differentiatedUiMediaDetails": {
                  "mediaType": "ADS_MEDIA_ENUM_IMAGE",
                  "lottie": {},
                  "video": {}
              }
          },
          "reviewsSummary": {},
          "displayType": "RESTAURANT_DISPLAY_TYPE_DEFAULT",
          "restaurantOfferPresentationInfo": {}
      },
      "analytics": {},
      "cta": {
          "link": "https://www.swiggy.com/restaurants/warmoven-cake-and-desserts-millars-road-vasanth-nagar-bangalore-402710",
          "type": "WEBLINK"
      }
  },
  {
      "info": {
          "id": "248316",
          "name": "Art Of Delight - Ice Creams, Sundaes And Desserts",
          "cloudinaryImageId": "boyv2da2hzpwwc779md4",
          "locality": "Bannergatta Main Road",
          "areaName": "Arekere",
          "costForTwo": "₹350 for two",
          "cuisines": [
              "Desserts",
              "Ice Cream",
              "Beverages"
          ],
          "avgRating": 4.5,
          "parentId": "474822",
          "avgRatingString": "4.5",
          "totalRatingsString": "1K+",
          "sla": {
              "deliveryTime": 48,
              "lastMileTravel": 11,
              "serviceability": "SERVICEABLE",
              "slaString": "45-50 mins",
              "lastMileTravelString": "11.0 km",
              "iconType": "ICON_TYPE_EMPTY"
          },
          "availability": {
              "nextCloseTime": "2024-04-19 00:00:00",
              "opened": true
          },
          "badges": {},
          "isOpen": true,
          "type": "F",
          "badgesV2": {
              "entityBadges": {
                  "imageBased": {},
                  "textBased": {},
                  "textExtendedBadges": {}
              }
          },
          "aggregatedDiscountInfoV3": {
              "header": "10% OFF",
              "subHeader": "UPTO ₹40"
          },
          "differentiatedUi": {
              "displayType": "ADS_UI_DISPLAY_TYPE_ENUM_DEFAULT",
              "differentiatedUiMediaDetails": {
                  "mediaType": "ADS_MEDIA_ENUM_IMAGE",
                  "lottie": {},
                  "video": {}
              }
          },
          "reviewsSummary": {},
          "displayType": "RESTAURANT_DISPLAY_TYPE_DEFAULT",
          "restaurantOfferPresentationInfo": {}
      },
      "analytics": {},
      "cta": {
          "link": "https://www.swiggy.com/restaurants/art-of-delight-ice-creams-sundaes-and-desserts-bannergatta-main-road-arekere-bangalore-248316",
          "type": "WEBLINK"
      }
  },
  {
      "info": {
          "id": "485078",
          "name": "Momo Zone - The Momo Company",
          "cloudinaryImageId": "id5fx1e0ptdvgnyo8rwi",
          "locality": "Padmavathi Complex",
          "areaName": "Vasanth Nagar",
          "costForTwo": "₹200 for two",
          "cuisines": [
              "Chinese",
              "Tibetan",
              "Fast Food"
          ],
          "avgRating": 3.7,
          "parentId": "382343",
          "avgRatingString": "3.7",
          "totalRatingsString": "100+",
          "sla": {
              "deliveryTime": 57,
              "lastMileTravel": 10.1,
              "serviceability": "SERVICEABLE",
              "slaString": "55-60 mins",
              "lastMileTravelString": "10.1 km",
              "iconType": "ICON_TYPE_EMPTY"
          },
          "availability": {
              "nextCloseTime": "2024-04-19 00:00:00",
              "opened": true
          },
          "badges": {},
          "isOpen": true,
          "type": "F",
          "badgesV2": {
              "entityBadges": {
                  "imageBased": {},
                  "textBased": {},
                  "textExtendedBadges": {}
              }
          },
          "aggregatedDiscountInfoV3": {
              "header": "60% OFF",
              "subHeader": "UPTO ₹120"
          },
          "differentiatedUi": {
              "displayType": "ADS_UI_DISPLAY_TYPE_ENUM_DEFAULT",
              "differentiatedUiMediaDetails": {
                  "mediaType": "ADS_MEDIA_ENUM_IMAGE",
                  "lottie": {},
                  "video": {}
              }
          },
          "reviewsSummary": {},
          "displayType": "RESTAURANT_DISPLAY_TYPE_DEFAULT",
          "restaurantOfferPresentationInfo": {}
      },
      "analytics": {},
      "cta": {
          "link": "https://www.swiggy.com/restaurants/momo-zone-the-momo-company-padmavathi-complex-vasanth-nagar-bangalore-485078",
          "type": "WEBLINK"
      }
  },
  {
      "info": {
          "id": "402714",
          "name": "Indiana Burgers",
          "cloudinaryImageId": "lflq8ulpskdypnl2gbak",
          "locality": "Millars Road",
          "areaName": "Vasanth Nagar",
          "costForTwo": "₹150 for two",
          "cuisines": [
              "Burgers",
              "American",
              "Fast Food",
              "Beverages",
              "Desserts"
          ],
          "avgRating": 3.7,
          "parentId": "5714",
          "avgRatingString": "3.7",
          "totalRatingsString": "100+",
          "sla": {
              "deliveryTime": 52,
              "lastMileTravel": 10.1,
              "serviceability": "SERVICEABLE",
              "slaString": "50-55 mins",
              "lastMileTravelString": "10.1 km",
              "iconType": "ICON_TYPE_EMPTY"
          },
          "availability": {
              "nextCloseTime": "2024-04-19 00:00:00",
              "opened": true
          },
          "badges": {
              "textExtendedBadges": [
                  {
                      "iconId": "guiltfree/GF_Logo_android_3x",
                      "shortDescription": "options available",
                      "fontColor": "#7E808C"
                  }
              ]
          },
          "isOpen": true,
          "type": "F",
          "badgesV2": {
              "entityBadges": {
                  "imageBased": {},
                  "textBased": {},
                  "textExtendedBadges": {
                      "badgeObject": [
                          {
                              "attributes": {
                                  "description": "",
                                  "fontColor": "#7E808C",
                                  "iconId": "guiltfree/GF_Logo_android_3x",
                                  "shortDescription": "options available"
                              }
                          }
                      ]
                  }
              }
          },
          "aggregatedDiscountInfoV3": {
              "header": "60% OFF",
              "subHeader": "UPTO ₹120"
          },
          "differentiatedUi": {
              "displayType": "ADS_UI_DISPLAY_TYPE_ENUM_DEFAULT",
              "differentiatedUiMediaDetails": {
                  "mediaType": "ADS_MEDIA_ENUM_IMAGE",
                  "lottie": {},
                  "video": {}
              }
          },
          "reviewsSummary": {},
          "displayType": "RESTAURANT_DISPLAY_TYPE_DEFAULT",
          "restaurantOfferPresentationInfo": {}
      },
      "analytics": {},
      "cta": {
          "link": "https://www.swiggy.com/restaurants/indiana-burgers-millars-road-vasanth-nagar-bangalore-402714",
          "type": "WEBLINK"
      }
  },
  {
      "info": {
          "id": "307291",
          "name": "Samosa Singh",
          "cloudinaryImageId": "77baefd8a5e319c828b4d7dff7260644",
          "locality": "3rd Stage",
          "areaName": "Banashankari",
          "costForTwo": "₹150 for two",
          "cuisines": [
              "Snacks",
              "North Indian",
              "Desserts",
              "Beverages"
          ],
          "avgRating": 4.1,
          "veg": true,
          "parentId": "5639",
          "avgRatingString": "4.1",
          "totalRatingsString": "1K+",
          "sla": {
              "deliveryTime": 53,
              "lastMileTravel": 11.1,
              "serviceability": "SERVICEABLE",
              "slaString": "50-55 mins",
              "lastMileTravelString": "11.1 km",
              "iconType": "ICON_TYPE_EMPTY"
          },
          "availability": {
              "nextCloseTime": "2024-04-19 00:00:00",
              "opened": true
          },
          "badges": {
              "imageBadges": [
                  {
                      "imageId": "v1695133679/badges/Pure_Veg111.png",
                      "description": "pureveg"
                  }
              ]
          },
          "isOpen": true,
          "type": "F",
          "badgesV2": {
              "entityBadges": {
                  "imageBased": {
                      "badgeObject": [
                          {
                              "attributes": {
                                  "description": "pureveg",
                                  "imageId": "v1695133679/badges/Pure_Veg111.png"
                              }
                          }
                      ]
                  },
                  "textBased": {},
                  "textExtendedBadges": {}
              }
          },
          "aggregatedDiscountInfoV3": {
              "header": "50% OFF",
              "subHeader": "UPTO ₹100"
          },
          "differentiatedUi": {
              "displayType": "ADS_UI_DISPLAY_TYPE_ENUM_DEFAULT",
              "differentiatedUiMediaDetails": {
                  "mediaType": "ADS_MEDIA_ENUM_IMAGE",
                  "lottie": {},
                  "video": {}
              }
          },
          "reviewsSummary": {},
          "displayType": "RESTAURANT_DISPLAY_TYPE_DEFAULT",
          "restaurantOfferPresentationInfo": {}
      },
      "analytics": {},
      "cta": {
          "link": "https://www.swiggy.com/restaurants/samosa-singh-3rd-stage-banashankari-bangalore-307291",
          "type": "WEBLINK"
      }
  },
  {
      "info": {
          "id": "402719",
          "name": "Cupcake Bliss Cake & Desserts",
          "cloudinaryImageId": "40f193d8b23afb2988489dac1258962f",
          "locality": "Padmavathi Complex",
          "areaName": "Vasanth Nagar",
          "costForTwo": "₹200 for two",
          "cuisines": [
              "Bakery",
              "Desserts",
              "Ice Cream",
              "Beverages"
          ],
          "avgRating": 3.5,
          "parentId": "66732",
          "avgRatingString": "3.5",
          "totalRatingsString": "100+",
          "sla": {
              "deliveryTime": 61,
              "lastMileTravel": 10.1,
              "serviceability": "SERVICEABLE",
              "slaString": "60-65 mins",
              "lastMileTravelString": "10.1 km",
              "iconType": "ICON_TYPE_EMPTY"
          },
          "availability": {
              "nextCloseTime": "2024-04-19 00:00:00",
              "opened": true
          },
          "badges": {},
          "isOpen": true,
          "type": "F",
          "badgesV2": {
              "entityBadges": {
                  "imageBased": {},
                  "textBased": {},
                  "textExtendedBadges": {}
              }
          },
          "aggregatedDiscountInfoV3": {
              "header": "60% OFF",
              "subHeader": "UPTO ₹120"
          },
          "differentiatedUi": {
              "displayType": "ADS_UI_DISPLAY_TYPE_ENUM_DEFAULT",
              "differentiatedUiMediaDetails": {
                  "mediaType": "ADS_MEDIA_ENUM_IMAGE",
                  "lottie": {},
                  "video": {}
              }
          },
          "reviewsSummary": {},
          "displayType": "RESTAURANT_DISPLAY_TYPE_DEFAULT",
          "restaurantOfferPresentationInfo": {}
      },
      "analytics": {},
      "cta": {
          "link": "https://www.swiggy.com/restaurants/cupcake-bliss-cake-and-desserts-padmavathi-complex-vasanth-nagar-bangalore-402719",
          "type": "WEBLINK"
      }
  },
  {
      "info": {
          "id": "43850",
          "name": "The Nosh House",
          "cloudinaryImageId": "t6c2esjgibs3nluwubvk",
          "locality": "Kasavanahalli",
          "areaName": "Sarjapur Road",
          "costForTwo": "₹600 for two",
          "cuisines": [
              "Continental",
              "Healthy Food",
              "Indian",
              "Desserts",
              "American",
              "Mediterranean",
              "Mexican",
              "Thai",
              "Asian",
              "Pan-Asian",
              "Home Food",
              "Bakery",
              "Snacks",
              "Pizzas",
              "Pastas",
              "Salads",
              "Italian",
              "Beverages"
          ],
          "avgRating": 4.5,
          "parentId": "21005",
          "avgRatingString": "4.5",
          "totalRatingsString": "10K+",
          "sla": {
              "deliveryTime": 54,
              "lastMileTravel": 8,
              "serviceability": "SERVICEABLE",
              "slaString": "50-55 mins",
              "lastMileTravelString": "8.0 km",
              "iconType": "ICON_TYPE_EMPTY"
          },
          "availability": {
              "nextCloseTime": "2024-04-12 22:30:00",
              "opened": true
          },
          "badges": {
              "textExtendedBadges": [
                  {
                      "iconId": "guiltfree/GF_Logo_android_3x",
                      "shortDescription": "options available",
                      "fontColor": "#7E808C"
                  }
              ]
          },
          "isOpen": true,
          "aggregatedDiscountInfoV2": {},
          "type": "C",
          "badgesV2": {
              "entityBadges": {
                  "imageBased": {},
                  "textBased": {},
                  "textExtendedBadges": {
                      "badgeObject": [
                          {
                              "attributes": {
                                  "description": "",
                                  "fontColor": "#7E808C",
                                  "iconId": "guiltfree/GF_Logo_android_3x",
                                  "shortDescription": "options available"
                              }
                          }
                      ]
                  }
              }
          },
          "differentiatedUi": {
              "displayType": "ADS_UI_DISPLAY_TYPE_ENUM_DEFAULT",
              "differentiatedUiMediaDetails": {
                  "mediaType": "ADS_MEDIA_ENUM_IMAGE",
                  "lottie": {},
                  "video": {}
              }
          },
          "reviewsSummary": {},
          "displayType": "RESTAURANT_DISPLAY_TYPE_DEFAULT",
          "restaurantOfferPresentationInfo": {}
      },
      "analytics": {},
      "cta": {
          "link": "https://www.swiggy.com/restaurants/the-nosh-house-kasavanahalli-sarjapur-road-bangalore-43850",
          "type": "WEBLINK"
      }
  },
  {
      "info": {
          "id": "29627",
          "name": "BIB - Breakfast in the Box",
          "cloudinaryImageId": "nbcpg5xk6ekrrngmkd0b",
          "locality": "1st block",
          "areaName": "Koramangala",
          "costForTwo": "₹350 for two",
          "cuisines": [
              "North Indian",
              "Street Food",
              "Chinese",
              "South Indian",
              "Continental",
              "Beverages"
          ],
          "avgRating": 4.4,
          "parentId": "45396",
          "avgRatingString": "4.4",
          "totalRatingsString": "10K+",
          "sla": {
              "deliveryTime": 30,
              "lastMileTravel": 1.4,
              "serviceability": "SERVICEABLE",
              "slaString": "25-30 mins",
              "lastMileTravelString": "1.4 km",
              "iconType": "ICON_TYPE_EMPTY"
          },
          "availability": {
              "nextCloseTime": "2024-04-12 14:30:00",
              "opened": true
          },
          "badges": {
              "textExtendedBadges": [
                  {
                      "iconId": "guiltfree/GF_Logo_android_3x",
                      "shortDescription": "options available",
                      "fontColor": "#7E808C"
                  }
              ]
          },
          "isOpen": true,
          "type": "F",
          "badgesV2": {
              "entityBadges": {
                  "imageBased": {},
                  "textBased": {},
                  "textExtendedBadges": {
                      "badgeObject": [
                          {
                              "attributes": {
                                  "description": "",
                                  "fontColor": "#7E808C",
                                  "iconId": "guiltfree/GF_Logo_android_3x",
                                  "shortDescription": "options available"
                              }
                          }
                      ]
                  }
              }
          },
          "aggregatedDiscountInfoV3": {
              "header": "30% OFF",
              "subHeader": "UPTO ₹75"
          },
          "differentiatedUi": {
              "displayType": "ADS_UI_DISPLAY_TYPE_ENUM_DEFAULT",
              "differentiatedUiMediaDetails": {
                  "mediaType": "ADS_MEDIA_ENUM_IMAGE",
                  "lottie": {},
                  "video": {}
              }
          },
          "reviewsSummary": {},
          "displayType": "RESTAURANT_DISPLAY_TYPE_DEFAULT",
          "restaurantOfferPresentationInfo": {}
      },
      "analytics": {},
      "cta": {
          "link": "https://www.swiggy.com/restaurants/bib-breakfast-in-the-box-1st-block-koramangala-bangalore-29627",
          "type": "WEBLINK"
      }
  },
  {
      "info": {
          "id": "323",
          "name": "Madurai Idly Shop",
          "cloudinaryImageId": "zompamr9uzayyf0po6mr",
          "locality": "HAL 2nd Stage",
          "areaName": "Indiranagar",
          "costForTwo": "₹150 for two",
          "cuisines": [
              "South Indian"
          ],
          "avgRating": 4.4,
          "veg": true,
          "parentId": "613",
          "avgRatingString": "4.4",
          "totalRatingsString": "10K+",
          "sla": {
              "deliveryTime": 35,
              "lastMileTravel": 6.1,
              "serviceability": "SERVICEABLE",
              "slaString": "30-35 mins",
              "lastMileTravelString": "6.1 km",
              "iconType": "ICON_TYPE_EMPTY"
          },
          "availability": {
              "nextCloseTime": "2024-04-13 00:45:00",
              "opened": true
          },
          "badges": {
              "imageBadges": [
                  {
                      "imageId": "v1695133679/badges/Pure_Veg111.png",
                      "description": "pureveg"
                  }
              ]
          },
          "isOpen": true,
          "type": "F",
          "badgesV2": {
              "entityBadges": {
                  "imageBased": {
                      "badgeObject": [
                          {
                              "attributes": {
                                  "description": "pureveg",
                                  "imageId": "v1695133679/badges/Pure_Veg111.png"
                              }
                          }
                      ]
                  },
                  "textBased": {},
                  "textExtendedBadges": {}
              }
          },
          "aggregatedDiscountInfoV3": {
              "header": "30% OFF",
              "subHeader": "UPTO ₹75"
          },
          "differentiatedUi": {
              "displayType": "ADS_UI_DISPLAY_TYPE_ENUM_DEFAULT",
              "differentiatedUiMediaDetails": {
                  "mediaType": "ADS_MEDIA_ENUM_IMAGE",
                  "lottie": {},
                  "video": {}
              }
          },
          "reviewsSummary": {},
          "displayType": "RESTAURANT_DISPLAY_TYPE_DEFAULT",
          "restaurantOfferPresentationInfo": {}
      },
      "analytics": {},
      "cta": {
          "link": "https://www.swiggy.com/restaurants/madurai-idly-shop-hal-2nd-stage-indiranagar-bangalore-323",
          "type": "WEBLINK"
      }
  },
  {
      "info": {
          "id": "284374",
          "name": "Lush - Renaissance Bengaluru Race Course Hotel By Marriott.",
          "cloudinaryImageId": "spff8i4rirrksqzps7jq",
          "locality": "Race Course Road",
          "areaName": "Race Course Road",
          "costForTwo": "₹800 for two",
          "cuisines": [
              "Indian",
              "Continental",
              "Oriental",
              "Asian"
          ],
          "avgRating": 4.3,
          "parentId": "12225",
          "avgRatingString": "4.3",
          "totalRatingsString": "100+",
          "sla": {
              "deliveryTime": 53,
              "lastMileTravel": 9.7,
              "serviceability": "SERVICEABLE",
              "slaString": "50-55 mins",
              "lastMileTravelString": "9.7 km",
              "iconType": "ICON_TYPE_EMPTY"
          },
          "availability": {
              "nextCloseTime": "2024-04-19 00:00:00",
              "opened": true
          },
          "badges": {
              "imageBadges": [
                  {
                      "imageId": "newg.png",
                      "description": "Gourmet"
                  }
              ]
          },
          "isOpen": true,
          "aggregatedDiscountInfoV2": {},
          "type": "F",
          "badgesV2": {
              "entityBadges": {
                  "imageBased": {
                      "badgeObject": [
                          {
                              "attributes": {
                                  "description": "Gourmet",
                                  "imageId": "newg.png"
                              }
                          }
                      ]
                  },
                  "textBased": {},
                  "textExtendedBadges": {}
              }
          },
          "differentiatedUi": {
              "displayType": "ADS_UI_DISPLAY_TYPE_ENUM_DEFAULT",
              "differentiatedUiMediaDetails": {
                  "mediaType": "ADS_MEDIA_ENUM_IMAGE",
                  "lottie": {},
                  "video": {}
              }
          },
          "reviewsSummary": {},
          "displayType": "RESTAURANT_DISPLAY_TYPE_DEFAULT",
          "restaurantOfferPresentationInfo": {}
      },
      "analytics": {},
      "cta": {
          "link": "https://www.swiggy.com/restaurants/lush-renaissance-bengaluru-race-course-hotel-by-marriott-race-course-road-bangalore-284374",
          "type": "WEBLINK"
      }
  }
]